fastpybuilder/DBConnect.py
fastpybuilder/RepositoryAnnotation.py
fastpybuilder/__init__.py
fastpybuilder/psql/windows/bin/clusterdb.exe
fastpybuilder/psql/windows/bin/createdb.exe
fastpybuilder/psql/windows/bin/createuser.exe
fastpybuilder/psql/windows/bin/dropdb.exe
fastpybuilder/psql/windows/bin/dropuser.exe
fastpybuilder/psql/windows/bin/ecpg.exe
fastpybuilder/psql/windows/bin/icudt67.dll
fastpybuilder/psql/windows/bin/icuin67.dll
fastpybuilder/psql/windows/bin/icuio67.dll
fastpybuilder/psql/windows/bin/icutu67.dll
fastpybuilder/psql/windows/bin/icuuc67.dll
fastpybuilder/psql/windows/bin/initdb.exe
fastpybuilder/psql/windows/bin/isolationtester.exe
fastpybuilder/psql/windows/bin/libcrypto-3-x64.dll
fastpybuilder/psql/windows/bin/libcurl.dll
fastpybuilder/psql/windows/bin/libcurl.lib
fastpybuilder/psql/windows/bin/libecpg.dll
fastpybuilder/psql/windows/bin/libecpg_compat.dll
fastpybuilder/psql/windows/bin/libiconv-2.dll
fastpybuilder/psql/windows/bin/libintl-9.dll
fastpybuilder/psql/windows/bin/liblz4.dll
fastpybuilder/psql/windows/bin/libpgtypes.dll
fastpybuilder/psql/windows/bin/libpq.dll
fastpybuilder/psql/windows/bin/libpq_pipeline.exe
fastpybuilder/psql/windows/bin/libpq_testclient.exe
fastpybuilder/psql/windows/bin/libpq_uri_regress.exe
fastpybuilder/psql/windows/bin/libssl-3-x64.dll
fastpybuilder/psql/windows/bin/libwinpthread-1.dll
fastpybuilder/psql/windows/bin/libxml2.dll
fastpybuilder/psql/windows/bin/libxslt.dll
fastpybuilder/psql/windows/bin/libzstd.dll
fastpybuilder/psql/windows/bin/oid2name.exe
fastpybuilder/psql/windows/bin/pg_amcheck.exe
fastpybuilder/psql/windows/bin/pg_archivecleanup.exe
fastpybuilder/psql/windows/bin/pg_basebackup.exe
fastpybuilder/psql/windows/bin/pg_checksums.exe
fastpybuilder/psql/windows/bin/pg_config.exe
fastpybuilder/psql/windows/bin/pg_controldata.exe
fastpybuilder/psql/windows/bin/pg_ctl.exe
fastpybuilder/psql/windows/bin/pg_dump.exe
fastpybuilder/psql/windows/bin/pg_dumpall.exe
fastpybuilder-0.1.39.dist-info/METADATA
fastpybuilder-0.1.39.dist-info/WHEEL
fastpybuilder-0.1.39.dist-info/top_level.txt
fastpybuilder-0.1.39.dist-info/RECORD
