Metadata-Version: 2.4
Name: fastpybuilder
Version: 0.1.39
Summary: python package to create backends faster, using PostgreSql and Flask, develop by Lenin Ospina Lamprea.
Author: Lenin Ospina Lamprea
Author-email: o.lamprea99@gmail.com
Classifier: Programming Language :: Python :: 3
Classifier: License :: OSI Approved :: MIT License
Classifier: Operating System :: OS Independent
Requires-Python: >=3.11
